README.txt
setup.py
py_w3c/__init__.py
py_w3c/exceptions.py
py_w3c/multipart.py
py_w3c.egg-info/PKG-INFO
py_w3c.egg-info/SOURCES.txt
py_w3c.egg-info/dependency_links.txt
py_w3c.egg-info/entry_points.txt
py_w3c.egg-info/top_level.txt
py_w3c/tests/__init__.py
py_w3c/tests/regression/__init__.py
py_w3c/tests/validators/__init__.py
py_w3c/tests/validators/html/__init__.py
py_w3c/tests/validators/html/test_validator.py
py_w3c/validators/__init__.py
py_w3c/validators/html/__init__.py
py_w3c/validators/html/validator.py