Metadata-Version: 1.0
Name: py-w3c
Version: 0.3.1
Summary: W3C services for python.
Home-page: http://pypi.python.org/pypi/py_w3c/
Author: Kazbek Byasov
Author-email: nmb.ten@gmail.com
License: LICENSE.txt
Platform: UNKNOWN
